PLATER/__init__.py
PLATER/examples/__init__.py
PLATER/integration_tests/__init__.py
PLATER/integration_tests/test_integration.py
PLATER/logs/__init__.py
PLATER/services/__init__.py
PLATER/services/app.py
PLATER/services/config.py
PLATER/services/models.py
PLATER/services/plater.conf
PLATER/services/util/__init__.py
PLATER/services/util/bl_helper.py
PLATER/services/util/graph_adapter.py
PLATER/services/util/logutil.py
PLATER/services/util/overlay.py
PLATER/services/util/question.py
PLATER/services/util/drivers/__init__.py
PLATER/services/util/drivers/neo4j_driver.py
PLATER/services/util/drivers/redis_driver.py
PLATER/services/util/drivers/redis_trapi_cypher_compiler.py
PLATER/templates/__init__.py
PLATER/tests/__init__.py
PLATER/tests/test_endpoint_factory.py
PLATER/tests/test_overlay.py
PLATER/tests/test_redis_transpiler.py
PLATER/tests/data/__init__.py
PLATER_GRAPH-1.9.8.dist-info/METADATA
PLATER_GRAPH-1.9.8.dist-info/WHEEL
PLATER_GRAPH-1.9.8.dist-info/dependency_links.txt
PLATER_GRAPH-1.9.8.dist-info/top_level.txt
PLATER_GRAPH-1.9.8.dist-info/RECORD
