Metadata-Version: 2.1
Name: PLATER-GRAPH
Version: 1.9.8
Summary: Graph DB interface for Translator API
Home-page: https://github.com/yaphetkg/plater.git
Maintainer: Renci
Maintainer-email: yaphetkg@renci.org
License: UNKNOWN
Platform: UNKNOWN
Classifier: Programming Language :: Python :: 3
Classifier: License :: OSI Approved :: MIT License
Classifier: Operating System :: OS Independent
Requires-Python: >=3.7
Requires-Dist: coverage
Requires-Dist: pyaml (==20.3.1)
Requires-Dist: pytest (==5.4.1)
Requires-Dist: pytest-asyncio (==0.14.0)
Requires-Dist: starlette (==0.13.6)
Requires-Dist: uvicorn (==0.11.7)
Requires-Dist: httpx
Requires-Dist: redis
